CS/__init__.py
CS/boot.py
CS/bsod.py
CS/calc.py
CS/cmd8.py
CS/core.py
CS/help.py
CS/info.py
CS/kernel.py
CS/login.py
CS/message.py
CS/os_info.py
CS/switch.py
CS/switch2.py
CS/thanks.py
CariboSystem_Embedded-5.1.dist-info/LICENSE
CariboSystem_Embedded-5.1.dist-info/METADATA
CariboSystem_Embedded-5.1.dist-info/WHEEL
CariboSystem_Embedded-5.1.dist-info/top_level.txt
CariboSystem_Embedded-5.1.dist-info/RECORD
