Metadata-Version: 2.1
Name: CariboSystem-Embedded
Version: 5.1
Summary: Python based miniature System
Author: Zanvok Corporation
License: UNKNOWN
Platform: UNKNOWN
Classifier: Programming Language :: Python :: 3
Classifier: License :: OSI Approved :: MIT License
Classifier: Operating System :: OS Independent
Requires-Python: >=3.7
License-File: LICENSE
